README.rst
setup.cfg
setup.py
dynamicTreeCut/R_func.py
dynamicTreeCut/__init__.py
dynamicTreeCut/__main__.py
dynamicTreeCut/df_apply.py
dynamicTreeCut/dynamicTreeCut.py
dynamicTreeCut.egg-info/PKG-INFO
dynamicTreeCut.egg-info/SOURCES.txt
dynamicTreeCut.egg-info/dependency_links.txt
dynamicTreeCut.egg-info/requires.txt
dynamicTreeCut.egg-info/top_level.txt