Metadata-Version: 1.0
Name: dynamicTreeCut
Version: 0.1.1
Summary: Dynamic Tree Cut
Home-page: https://github.com/kylessmith/dynamicTreeCut
Author: Kyle S. Smith
Author-email: kyle.smith@stjude.org
License: GPL-3 Licenses
Platform: UNKNOWN
